MANIFEST.in
README.md
setup.py
bin/diff-axe
bin/dt-axe
dt8xp/__init__.py
dt8xp/dt8xp.py
dt8xp.egg-info/PKG-INFO
dt8xp.egg-info/SOURCES.txt
dt8xp.egg-info/dependency_links.txt
dt8xp.egg-info/entry_points.txt
dt8xp.egg-info/not-zip-safe
dt8xp.egg-info/requires.txt
dt8xp.egg-info/top_level.txt
dt8xp/tokens/AxeTokens.xml
dt8xp/tokens/DCS8.xml
dt8xp/tokens/GrammerTokens.xml
dt8xp/tokens/NoLib.xml
dt8xp/tokens/Prizm.xml
dt8xp/tokens/TI-73.xml
dt8xp/tokens/TI-82.xml
dt8xp/tokens/TI-84+CSE.xml
dt8xp/tokens/Tokens.xml