Metadata-Version: 1.0
Name: dt8xp
Version: 0.2
Summary: Detokenize 8xp calculator program files
Home-page: UNKNOWN
Author: Koen van Vliet
Author-email: 8by8mail@gmail.com
License: MIT
Platform: UNKNOWN
